homekeeper/__init__.py
homekeeper/cli.py
homekeeper/cli_cleanup_test.py
homekeeper/cli_keep_test.py
homekeeper/cli_unkeep_test.py
homekeeper/cli_version_test.py
homekeeper/config.py
homekeeper/config_test.py
homekeeper/exceptions.py
homekeeper/homekeeper_test.py
homekeeper/lib.py
homekeeper/lib_test.py
homekeeper/symlink.py
homekeeper/symlink_cleanup_test.py
homekeeper/symlink_create_test.py
homekeeper/symlink_restore_test.py
homekeeper/testing.py
homekeeper-5.1.0.dist-info/LICENSE
homekeeper-5.1.0.dist-info/METADATA
homekeeper-5.1.0.dist-info/WHEEL
homekeeper-5.1.0.dist-info/entry_points.txt
homekeeper-5.1.0.dist-info/top_level.txt
homekeeper-5.1.0.dist-info/RECORD
