Metadata-Version: 2.1
Name: homekeeper
Version: 5.1.0
Summary: Symlinks your dotfiles from anywhere to your home directory.
Home-page: https://github.com/retiman/homekeeper
Author: Min Huang
Author-email: min.huang@alumni.usc.edu
License: MIT
Platform: any
Classifier: Development Status :: 5 - Production/Stable
Classifier: Programming Language :: Python :: 3.5
Classifier: Programming Language :: Python :: 3.6
Classifier: Programming Language :: Python :: 3.7
Classifier: Programming Language :: Python :: 3.8
Classifier: Topic :: Utilities
Requires-Dist: click (>=7.1.2)
